LICENSE
MANIFEST.in
README.md
setup.cfg
setup.py
django_djavue.egg-info/PKG-INFO
django_djavue.egg-info/SOURCES.txt
django_djavue.egg-info/dependency_links.txt
django_djavue.egg-info/top_level.txt
djavue/__init__.py
djavue/component.py
djavue/component_list.py
djavue/views.py
djavue/renderers/__init__.py
djavue/renderers/base.py
djavue/renderers/vuetify.py
djavue/tests/__init__.py
djavue/tests/component.py
djavue/tests/renderer.py
prototype/__init__.py
prototype/asgi.py
prototype/settings.py
prototype/urls.py
prototype/wsgi.py